[
  {
    "id": "7e670e57890ffedf",
    "title": "Fralda Turma da Mônica Baby XG 168 unidades",
    "price_now": 113.0,
    "price_was": 170.72,
    "discount_pct": 34,
    "url": "https://s.shopee.com.br/LlqDOA8nc?af_id=18328861131",
    "image": "https://i.promobit.com.br/1200/437556912717847426078207988179.jpg",
    "source": "promobit",
    "niche": "motherhood",
    "added_at": "2026-07-22T18:01:31.715720"
  },
  {
    "id": "fcc81de0909470c6",
    "title": "Fralda Turma da Mônica Baby M 200unidades",
    "price_now": 113.0,
    "price_was": 170.72,
    "discount_pct": 34,
    "url": "https://s.shopee.com.br/9pcvXKMkyN?af_id=18328861131",
    "image": "https://i.promobit.com.br/1200/418979132217847430295294721919.jpg",
    "source": "promobit",
    "niche": "motherhood",
    "added_at": "2026-07-22T18:01:19.601832"
  },
  {
    "id": "97177c2f8ae1ff88",
    "title": "Fralda Turma da Mônica Baby XXG 144 unidades",
    "price_now": 113.0,
    "price_was": 171.94,
    "discount_pct": 34,
    "url": "https://s.shopee.com.br/7AcAMQpbi2?af_id=18328861131",
    "image": "https://i.promobit.com.br/1200/263035396017847430372784780420.jpg",
    "source": "promobit",
    "niche": "motherhood",
    "added_at": "2026-07-22T18:01:09.297684"
  },
  {
    "id": "73c591e5845d00ed",
    "title": "Babá Eletrônica com Monitor Visão Noturna Áudio Bidirecional Sensor de Temperatura Monitor Infantil Digital",
    "price_now": 228.9,
    "price_was": 595.43,
    "discount_pct": 62,
    "url": "https://s.shopee.com.br/1VxnbX9xg2?af_id=18328861131",
    "image": "https://i.promobit.com.br/1200/444223816517847426734086263762.jpg",
    "source": "promobit",
    "niche": "motherhood",
    "added_at": "2026-07-22T18:00:58.215286"
  },
  {
    "id": "8aad082245f74225",
    "title": "Manta Cobertor 120x100 Ultra Soft Antialérgico de Algodão para Bebês - ColorBaby",
    "price_now": 26.39,
    "price_was": 49.98,
    "discount_pct": 47,
    "url": "https://s.shopee.com.br/qi6dFxrO8?af_id=18328861131",
    "image": "https://i.promobit.com.br/1200/392986986017847329526701900844.jpg",
    "source": "promobit",
    "niche": "motherhood",
    "added_at": "2026-07-22T15:20:51.249536"
  },
  {
    "id": "1b3a779623bbd1be",
    "title": "Máquina de Ruído Branco Infantil - Aparelho de Som para Dormir Luz Noturna USB Ideal para Bebês e Relaxamento",
    "price_now": 61.98,
    "price_was": 157.45,
    "discount_pct": 61,
    "url": "https://s.shopee.com.br/9fJV7CnMG6?af_id=18328861131",
    "image": "https://i.promobit.com.br/1200/145897328517847310284826971896.jpg",
    "source": "promobit",
    "niche": "motherhood",
    "added_at": "2026-07-22T14:50:47.498101"
  },
  {
    "id": "6385b8fc45e97acf",
    "title": "Fralda Pampers Supersec XXG 66 unidades",
    "price_now": 74.25,
    "price_was": 145.57,
    "discount_pct": 49,
    "url": "https://s.shopee.com.br/2LWuJtakz7?af_id=18328861131",
    "image": "https://i.promobit.com.br/1200/479704834117847276071682863463.jpg",
    "source": "promobit",
    "niche": "motherhood",
    "added_at": "2026-07-22T13:50:56.696692"
  },
  {
    "id": "6ba3d9785c8bf9ad",
    "title": "Fralda Pampers Supersec M 90 unidades",
    "price_now": 74.25,
    "price_was": 145.57,
    "discount_pct": 49,
    "url": "https://s.shopee.com.br/6VMTHYKl2F?af_id=18328861131",
    "image": "https://i.promobit.com.br/1200/902318242717847276117090963891.jpg",
    "source": "promobit",
    "niche": "motherhood",
    "added_at": "2026-07-22T13:50:51.284292"
  },
  {
    "id": "e06eb40d8cc4b5b5",
    "title": "Fralda Pampers Supersec G 80 unidades",
    "price_now": 74.25,
    "price_was": 145.57,
    "discount_pct": 49,
    "url": "https://s.shopee.com.br/2g9kiVe1bz?af_id=18328861131",
    "image": "https://i.promobit.com.br/1200/309407827417847276138514416276.jpg",
    "source": "promobit",
    "niche": "motherhood",
    "added_at": "2026-07-22T13:50:45.595817"
  },
  {
    "id": "d4ca7e8f4039a69d",
    "title": "Johnson's Baby Shampoo Para Bebê Para Cabelos Claros, 750ml",
    "price_now": 29.14,
    "price_was": 53.99,
    "discount_pct": 46,
    "url": "https://www.amazon.com.br/dp/B07DHRHZDR?tag=amamaeencontr-20",
    "image": "https://i.promobit.com.br/1200/227639774917847261739250658259.jpg",
    "source": "promobit",
    "niche": "motherhood",
    "added_at": "2026-07-22T13:20:50.485217"
  },
  {
    "id": "5ecc8ee097f193f3",
    "title": "Assento De Carro Infantil Elevação Fit Up 15-36kg Maxi Baby (2 cores)",
    "price_now": 62.32,
    "price_was": 118.03,
    "discount_pct": 47,
    "url": "https://s.shopee.com.br/9V04pLzMH0?af_id=18328861131",
    "image": "https://i.promobit.com.br/1200/897644932517847261116896514231.jpg",
    "source": "promobit",
    "niche": "motherhood",
    "added_at": "2026-07-22T13:20:42.210585"
  },
  {
    "id": "7ae24bea8c8dea2d",
    "title": "Fralda Babysec Ultrasec XXG 48 unidades",
    "price_now": 55.99,
    "price_was": 87.49,
    "discount_pct": 36,
    "url": "https://s.shopee.com.br/60QCbgfM0S?af_id=18328861131",
    "image": "https://i.promobit.com.br/1200/697142387117847232858411122063.jpg",
    "source": "promobit",
    "niche": "motherhood",
    "added_at": "2026-07-22T12:41:06.419780"
  }
]