[
  {
    "id": "cac2187ce7805e8e",
    "title": "Bicicleta De Equilibrio Andador Infantil Sem Pedal Para Crianças (rosa)",
    "price_now": 64.6,
    "price_was": 169.9,
    "discount_pct": 62,
    "url": "https://www.amazon.com.br/dp/B0DLHYSGPG?tag=amamaeencontr-20",
    "image": "https://i.promobit.com.br/1200/210141536517840647395857797413.jpg",
    "source": "promobit",
    "niche": "motherhood",
    "added_at": "2026-07-14T21:51:04.323525"
  },
  {
    "id": "61ca7af745eca3ae",
    "title": "Carrinho Chicco Glee 0m+ Até 22kg Fechamento Automático Prático",
    "price_now": 999.0,
    "price_was": 1899.0,
    "discount_pct": 47,
    "url": "https://www.amazon.com.br/dp/B0C5S8NW3X?tag=amamaeencontr-20",
    "image": "https://i.promobit.com.br/1200/898513964317840588536803577781.jpg",
    "source": "promobit",
    "niche": "motherhood",
    "added_at": "2026-07-14T20:01:11.529531"
  },
  {
    "id": "4b8bb878cc5a88f6",
    "title": "Kit 2 Prendedores De Chupeta Coala Buba",
    "price_now": 19.7,
    "price_was": 29.9,
    "discount_pct": 34,
    "url": "https://www.amazon.com.br/dp/B0B3F6BXLH?tag=amamaeencontr-20",
    "image": "https://i.promobit.com.br/1200/953952670017840511275933564235.jpg",
    "source": "promobit",
    "niche": "motherhood",
    "added_at": "2026-07-14T18:01:09.887975"
  },
  {
    "id": "7b29357850fafdb0",
    "title": "Casaco Teddy Infantil Capuz Touca com Zíper (Tam. 1 a 16 Anos, Diversas cores)",
    "price_now": 23.5,
    "price_was": 69.12,
    "discount_pct": 66,
    "url": "https://s.shopee.com.br/80B4Ljnuwi?af_id=18328861131",
    "image": "https://i.promobit.com.br/1200/922762923517840386413272355614.jpg",
    "source": "promobit",
    "niche": "motherhood",
    "added_at": "2026-07-14T14:31:04.711526"
  },
  {
    "id": "c5b598b6687570fc",
    "title": "Huggies Fralda Descartável Premium Natural Care Rn - 34 Un",
    "price_now": 29.9,
    "price_was": 43.59,
    "discount_pct": 31,
    "url": "https://www.amazon.com.br/dp/B095R9CKYR?tag=amamaeencontr-20",
    "image": "https://i.promobit.com.br/1200/548122866317839813926950463422.jpg",
    "source": "promobit",
    "niche": "motherhood",
    "added_at": "2026-07-13T22:41:00.768375"
  },
  {
    "id": "72d2e33e5216aa88",
    "title": "Fralda Descartável Huggies Máxima Proteção Tamanho G 66 Unidades – Nova Fralda Supreme Care Aberta Com Tecnologia Xtra-flex, Canais Em X Que Se",
    "price_now": 69.99,
    "price_was": 116.9,
    "discount_pct": 40,
    "url": "https://www.amazon.com.br/dp/B0BQ42779Q?tag=amamaeencontr-20",
    "image": "https://i.promobit.com.br/1200/498482988217839771914219828394.jpg",
    "source": "promobit",
    "niche": "motherhood",
    "added_at": "2026-07-13T21:21:01.686819"
  },
  {
    "id": "ff75e61d3763482a",
    "title": "Fralda Personal Baby Premium Protection XG 26 Unidades",
    "price_now": 28.49,
    "price_was": 46.38,
    "discount_pct": 39,
    "url": "https://www.amazon.com.br/dp/B0C3FQQVLH?tag=amamaeencontr-20",
    "image": "https://i.promobit.com.br/1200/405409484417839708315278317971.jpg",
    "source": "promobit",
    "niche": "motherhood",
    "added_at": "2026-07-13T19:31:12.575119"
  },
  {
    "id": "00c9792c6a84995d",
    "title": "Fralda Personal Baby Premium Pants G 4 pacotes 168 unidades",
    "price_now": 182.21,
    "price_was": 297.71,
    "discount_pct": 39,
    "url": "https://www.amazon.com.br/dp/B0DF9PBG3B?tag=amamaeencontr-20",
    "image": "https://i.promobit.com.br/1200/798789246917839689214349466265.jpg",
    "source": "promobit",
    "niche": "motherhood",
    "added_at": "2026-07-13T19:01:11.109715"
  },
  {
    "id": "b823039940dba920",
    "title": "Fralda Personal Baby Premium Protection RN ao P 40 unidades",
    "price_now": 31.52,
    "price_was": 46.38,
    "discount_pct": 32,
    "url": "https://www.amazon.com.br/dp/B0C3FSF7KF?tag=amamaeencontr-20",
    "image": "https://i.promobit.com.br/1200/423841897217839680723574828240.jpg",
    "source": "promobit",
    "niche": "motherhood",
    "added_at": "2026-07-13T18:51:07.492753"
  },
  {
    "id": "de9fda93b8e02baf",
    "title": "Fralda Personal Baby Premium Protection M 34 unidades",
    "price_now": 31.52,
    "price_was": 46.38,
    "discount_pct": 32,
    "url": "https://www.amazon.com.br/dp/B0C3FK76V3?tag=amamaeencontr-20",
    "image": "https://i.promobit.com.br/1200/900984947717839680807264500905.jpg",
    "source": "promobit",
    "niche": "motherhood",
    "added_at": "2026-07-13T18:50:58.456815"
  },
  {
    "id": "e0f00c0c6125e09a",
    "title": "Kit Banho Bebê Orgânico (1 Shampoo 200ml, 1 Condicionador 200ml, 1 Colônia Sem Álcool 30ml)",
    "price_now": 44.9,
    "price_was": 70.16,
    "discount_pct": 36,
    "url": "https://s.shopee.com.br/9zw7PMBiat?lp=aff&af_id=18328861131",
    "image": "https://i.promobit.com.br/1200/554371698317839669485532261505.jpg",
    "source": "promobit",
    "niche": "motherhood",
    "added_at": "2026-07-13T18:31:12.902803"
  },
  {
    "id": "c24044f1533529c5",
    "title": "Lenço Umedecido Johnson's Baby Recém-Nascido Sem Perfume 48 unidades",
    "price_now": 9.8,
    "price_was": 18.49,
    "discount_pct": 47,
    "url": "https://www.amazon.com.br/dp/B07DHSFWBL?tag=amamaeencontr-20",
    "image": "https://i.promobit.com.br/1200/459905720117839640185113421732.jpg",
    "source": "promobit",
    "niche": "motherhood",
    "added_at": "2026-07-13T17:41:00.042849"
  }
]