[
  {
    "id": "7ae24bea8c8dea2d",
    "title": "Fralda Babysec Ultrasec XXG 48 unidades",
    "price_now": 55.99,
    "price_was": 87.49,
    "discount_pct": 36,
    "url": "https://s.shopee.com.br/60QCbgfM0S?af_id=18328861131",
    "image": "https://i.promobit.com.br/1200/697142387117847232858411122063.jpg",
    "source": "promobit",
    "niche": "motherhood",
    "added_at": "2026-07-22T12:41:06.419780"
  },
  {
    "id": "e132e9ac09abed94",
    "title": "Fralda Babysec Ultrasec M 68 unidades",
    "price_now": 55.99,
    "price_was": 87.49,
    "discount_pct": 36,
    "url": "https://s.shopee.com.br/6AjcnziqQk?af_id=18328861131",
    "image": "https://i.promobit.com.br/1200/574259637517847232889921646162.jpg",
    "source": "promobit",
    "niche": "motherhood",
    "added_at": "2026-07-22T12:40:56.035987"
  },
  {
    "id": "eab56d529f2eefb6",
    "title": "Fralda Babysec Ultrasec XG 56 unidades",
    "price_now": 55.99,
    "price_was": 87.49,
    "discount_pct": 36,
    "url": "https://s.shopee.com.br/111WeV1YEj?af_id=18328861131",
    "image": "https://i.promobit.com.br/1200/334349269517847232905212538590.jpg",
    "source": "promobit",
    "niche": "motherhood",
    "added_at": "2026-07-22T12:40:45.116590"
  },
  {
    "id": "ed487348d0ee3e48",
    "title": "Fralda Huggies Natural Care RN 34 Unidades",
    "price_now": 28.4,
    "price_was": 43.59,
    "discount_pct": 35,
    "url": "https://www.amazon.com.br/dp/B095R9CKYR?tag=amamaeencontr-20",
    "image": "https://i.promobit.com.br/1200/269535511717847213047595982933.jpg",
    "source": "promobit",
    "niche": "motherhood",
    "added_at": "2026-07-22T12:10:44.261566"
  },
  {
    "id": "8112ad0f34537afe",
    "title": "Condicionador Natura Mamãe e Bebê 200ml",
    "price_now": 29.92,
    "price_was": 48.07,
    "discount_pct": 38,
    "url": "https://s.shopee.com.br/111WaAweZN?lp=aff&af_id=18328861131",
    "image": "https://i.promobit.com.br/1200/301025184817847195114322774509.jpg",
    "source": "promobit",
    "niche": "motherhood",
    "added_at": "2026-07-22T11:40:53.263030"
  },
  {
    "id": "c80026a4d9411095",
    "title": "Livro Sensorial Educativo Infantil Montessori",
    "price_now": 40.96,
    "price_was": 151.72,
    "discount_pct": 73,
    "url": "https://s.shopee.com.br/3B61AZMIsd?af_id=18328861131",
    "image": "https://i.promobit.com.br/1200/205164014917847198693328187342.jpg",
    "source": "promobit",
    "niche": "motherhood",
    "added_at": "2026-07-22T11:40:45.386848"
  },
  {
    "id": "40fd19806339e518",
    "title": "Personal Fralda Baby Premium Protection P, 40 Unidades",
    "price_now": 30.49,
    "price_was": 46.38,
    "discount_pct": 34,
    "url": "https://www.amazon.com.br/dp/B0C3FSF7KF?tag=amamaeencontr-20",
    "image": "https://i.promobit.com.br/1200/524464297717847185477066115194.jpg",
    "source": "promobit",
    "niche": "motherhood",
    "added_at": "2026-07-22T11:20:40.535412"
  },
  {
    "id": "0244a8ca4d494bf3",
    "title": "Fralda Personal Baby Premium Protection M 34 unidades",
    "price_now": 28.4,
    "price_was": 46.38,
    "discount_pct": 39,
    "url": "https://www.amazon.com.br/dp/B0C3FK76V3?tag=amamaeencontr-20",
    "image": "https://i.promobit.com.br/1200/416033634617847171648273778098.jpg",
    "source": "promobit",
    "niche": "motherhood",
    "added_at": "2026-07-22T10:50:35.894333"
  },
  {
    "id": "b4e642826d6a861e",
    "title": "Fralda Patrulha Canina Cremer - 5 Unidades",
    "price_now": 26.69,
    "price_was": 47.44,
    "discount_pct": 44,
    "url": "https://www.amazon.com.br/dp/B09KX6WYGB?tag=amamaeencontr-20",
    "image": "https://i.promobit.com.br/1200/881149496617846671874865375472.jpg",
    "source": "promobit",
    "niche": "motherhood",
    "added_at": "2026-07-21T21:00:53.207163"
  },
  {
    "id": "bec2be620d587b51",
    "title": "Fralda Pom Pom Protek Proteção de Mãe XG 20 Unidades",
    "price_now": 18.89,
    "price_was": 30.17,
    "discount_pct": 37,
    "url": "https://www.amazon.com.br/dp/B093G99QBH?tag=amamaeencontr-20",
    "image": "https://i.promobit.com.br/1200/266794977317846458317589983645.jpg",
    "source": "promobit",
    "niche": "motherhood",
    "added_at": "2026-07-21T15:01:02.753784"
  },
  {
    "id": "801d29713055f9c8",
    "title": "Fralda Pom Pom Protek Proteção de Mãe Jumbo XG 20 Unidades",
    "price_now": 19.88,
    "price_was": 30.17,
    "discount_pct": 34,
    "url": "https://www.amazon.com.br/dp/B093G99QBH?tag=amamaeencontr-20",
    "image": "https://i.promobit.com.br/1200/925781179417846439754782933654.jpg",
    "source": "promobit",
    "niche": "motherhood",
    "added_at": "2026-07-21T14:30:52.884111"
  },
  {
    "id": "ce1eac8c74705d32",
    "title": "Sandália Babuche Infantil Antiderrapante (Tam. 19 ao 32, Diversas cores)",
    "price_now": 19.9,
    "price_was": 60.3,
    "discount_pct": 67,
    "url": "https://s.shopee.com.br/18xpNQbpP?af_id=18328861131",
    "image": "https://i.promobit.com.br/1200/626938873217846347941814103676.jpg",
    "source": "promobit",
    "niche": "motherhood",
    "added_at": "2026-07-21T12:00:57.215161"
  }
]